Pyserva/JupyterNotebookHelper.py
Pyserva/SampleReport.py
Pyserva/StandaloneApiHelper.py
Pyserva/__init__.py
Pyserva-1.5.1.0.dist-info/LICENSE.txt
Pyserva-1.5.1.0.dist-info/METADATA
Pyserva-1.5.1.0.dist-info/WHEEL
Pyserva-1.5.1.0.dist-info/top_level.txt
Pyserva-1.5.1.0.dist-info/RECORD
