Metadata-Version: 2.1
Name: Pyserva
Version: 1.5.1.0
Summary: The Senserva Python library
Home-page: https://github.com/Senserva-LLC/Pyserva
Author: Thomas Dolan
Author-email: tj@senserva.com
License: UNKNOWN
Project-URL: Bug Tracker, https://github.com/Senserva-LLC/Pyserva/issues
Platform: UNKNOWN
Classifier: Programming Language :: Python :: 3
Classifier: License :: OSI Approved :: MIT License
Classifier: Operating System :: OS Independent
Requires-Python: >=3.6
License-File: LICENSE.txt
